georunes/__init__.py
georunes/data/References.txt
georunes/data/Reservoirs.csv
georunes/modmin/__init__.py
georunes/modmin/norm/__init__.py
georunes/modmin/norm/cipw.py
georunes/modmin/optim/__init__.py
georunes/modmin/optim/base.py
georunes/modmin/optim/bvls.py
georunes/modmin/optim/gd.py
georunes/modmin/optim/nnls.py
georunes/modmin/optim/randsearch.py
georunes/modmin/struct/__init__.py
georunes/modmin/struct/apfu.py
georunes/petromod/__init__.py
georunes/petromod/finders/__init__.py
georunes/petromod/finders/cumulate_finder.py
georunes/petromod/modelers/__init__.py
georunes/petromod/modelers/batch.py
georunes/petromod/modelers/mass_balance.py
georunes/petromod/modelers/partition.py
georunes/petromod/modelers/rayleigh.py
georunes/petromod/viewer/__init__.py
georunes/petromod/viewer/_coming.py
georunes/petromod/viewer/tk/__init__.py
georunes/petromod/viewer/tk/base_viewer.py
georunes/petromod/viewer/tk/fract_viewer.py
georunes/petromod/viewer/tk/mass_balance_viewer.py
georunes/petromod/viewer/tk/spider_viewer.py
georunes/plot/__init__.py
georunes/plot/base.py
georunes/plot/helpers.py
georunes/plot/legend.py
georunes/plot/spider.py
georunes/plot/binary/__init__.py
georunes/plot/binary/debonlefortba.py
georunes/plot/binary/debonlefortpq.py
georunes/plot/binary/delaroche.py
georunes/plot/binary/frost.py
georunes/plot/binary/pearce.py
georunes/plot/binary/peccetaylor.py
georunes/plot/binary/ratiosversus.py
georunes/plot/binary/shand.py
georunes/plot/binary/sialkali.py
georunes/plot/binary/versus.py
georunes/plot/piper/__init__.py
georunes/plot/piper/helpers.py
georunes/plot/piper/lines.py
georunes/plot/piper/piper_axe_subplot.py
georunes/plot/piper/piper_diag.py
georunes/plot/piper/plotting.py
georunes/plot/ternary/__init__.py
georunes/plot/ternary/afm.py
georunes/plot/ternary/anabor.py
georunes/plot/ternary/jensen.py
georunes/plot/ternary/nesbitt_young.py
georunes/plot/ternary/qap.py
georunes/plot/ternary/ternbase.py
georunes/plot/threed/__init__.py
georunes-1.0.0.dist-info/licenses/LICENSE
georunes-1.0.0.dist-info/METADATA
georunes-1.0.0.dist-info/WHEEL
georunes-1.0.0.dist-info/top_level.txt
georunes-1.0.0.dist-info/RECORD
