Metadata-Version: 2.4
Name: georunes
Version: 1.0.0
Summary: Tools for geochemical visualization and modeling
Home-page: https://github.com/dugucrypter/georunes
Author: Wiledio Marc-Emile Bonzi
Author-email: wiledio.bonzi@gmail.com
License: MIT
Project-URL: Source, https://github.com/dugucrypter/georunes
Keywords: geochemistry,diagrams,oxides,chemical elements,modeling,fitting
Classifier: Intended Audience :: Science/Research
Classifier: Operating System :: OS Independent
Classifier: Programming Language :: Python :: 3
Classifier: License :: OSI Approved :: MIT License
Requires-Python: >=3.6
License-File: LICENSE
Requires-Dist: matplotlib
Requires-Dist: numpy
Requires-Dist: scipy
Requires-Dist: pandas
Requires-Dist: python-ternary
Requires-Dist: xlsxwriter
Dynamic: license-file
Dynamic: requires-dist
Dynamic: requires-python
